pnt_datasets/__init__.py
pnt_datasets/ipin/__init__.py
pnt_datasets/ipin/IPIN_2022_T8/D0_measurements.parquet
pnt_datasets/ipin/IPIN_2022_T8/D0_reference.parquet
pnt_datasets/ipin/IPIN_2022_T8/D1_measurements.parquet
pnt_datasets/ipin/IPIN_2022_T8/D1_reference.parquet
pnt_datasets/ipin/IPIN_2022_T8/nodes.parquet
pnt_datasets/ipin/IPIN_2023_T8/D2_measurements.parquet
pnt_datasets/ipin/IPIN_2023_T8/D2_reference.parquet
pnt_datasets/ipin/IPIN_2023_T8/D5_measurements.parquet
pnt_datasets/ipin/IPIN_2023_T8/D5_reference.parquet
pnt_datasets/ipin/IPIN_2023_T8/D6_measurements.parquet
pnt_datasets/ipin/IPIN_2023_T8/D6_reference.parquet
pnt_datasets/ipin/IPIN_2023_T8/D8_measurements.parquet
pnt_datasets/ipin/IPIN_2023_T8/D8_reference.parquet
pnt_datasets/ipin/IPIN_2023_T8/nodes.parquet
pnt_datasets-0.2.2.dist-info/LICENSE
pnt_datasets-0.2.2.dist-info/METADATA
pnt_datasets-0.2.2.dist-info/WHEEL
pnt_datasets-0.2.2.dist-info/top_level.txt
pnt_datasets-0.2.2.dist-info/RECORD
